shallow_appify/__init__.py
shallow_appify/__main__.py
shallow_appify/_version.py
shallow_appify/dmg_background.png
shallow_appify/shallow_appify.py
shallow_appify/plugins/__init__.py
shallow_appify/plugins/python.py
shallow_appify/plugins/util/__init__.py
shallow_appify/plugins/util/binary_replace.py
shallow_appify/plugins/util/command.py
shallow_appify/plugins/util/libpatch.py
shallow_appify-0.4.4.dist-info/LICENSE
shallow_appify-0.4.4.dist-info/METADATA
shallow_appify-0.4.4.dist-info/WHEEL
shallow_appify-0.4.4.dist-info/entry_points.txt
shallow_appify-0.4.4.dist-info/top_level.txt
shallow_appify-0.4.4.dist-info/RECORD
